MANIFEST.in
setup.py
django_postgres/__init__.py
django_postgres/bitstrings.py
django_postgres/citext.py
django_postgres/six.py
django_postgres/view.py
django_postgres/management/__init__.py
django_postgres/management/commands/__init__.py
django_postgres/management/commands/sync_pgviews.py
django_postgres_pebble.egg-info/PKG-INFO
django_postgres_pebble.egg-info/SOURCES.txt
django_postgres_pebble.egg-info/dependency_links.txt
django_postgres_pebble.egg-info/requires.txt
django_postgres_pebble.egg-info/top_level.txt