Metadata-Version: 1.0
Name: django-postgres-pebble
Version: 0.0.5
Summary: First-class Postgres feature support for the Django ORM. (Pebble Branch)
Home-page: UNKNOWN
Author: Scott Walton
Author-email: scw@talktopebble.co.uk
License: Public Domain
Platform: UNKNOWN
